alistair/__init__.py
alistair/review.py
alistair-0.1.dist-info/METADATA
alistair-0.1.dist-info/WHEEL
alistair-0.1.dist-info/top_level.txt
alistair-0.1.dist-info/RECORD
