Metadata-Version: 2.1
Name: alistair
Version: 0.1
Summary: Miscellaneous tools
Home-page: https://github.com/alistairewj/alistair
Author: Alistair Johnson
Author-email: aewj@mit.edu
License: UNKNOWN
Platform: UNKNOWN
Classifier: Programming Language :: Python
Classifier: Programming Language :: Python :: 3
Requires-Dist: numpy (>=1.16.2)
